llm_provider/__init__.py
llm_provider/base_image_provider.py
llm_provider/base_provider.py
llm_provider/base_speech_provider.py
llm_provider/factory.py
llm_provider/image_factory.py
llm_provider/settings.py
llm_provider/speech_factory.py
llm_provider/providers/__init__.py
llm_provider/providers/anthropic_provider.py
llm_provider/providers/gemini_provider.py
llm_provider/providers/google_speech_provider.py
llm_provider/providers/ollama_provider.py
llm_provider/providers/openai_image_provider.py
llm_provider/providers/openai_provider.py
llm_provider/providers/openai_speech_provider.py
llm_provider/providers/replicate_image_provider.py
llm_provider/providers/vertexai_provider.py
llm_provider/utils/__init__.py
llm_provider/utils/config.py
llm_provider/utils/exceptions.py
llm_provider/utils/logger.py
llm_provider_factory-0.6.0.dist-info/licenses/LICENSE
llm_provider_factory-0.6.0.dist-info/METADATA
llm_provider_factory-0.6.0.dist-info/WHEEL
llm_provider_factory-0.6.0.dist-info/top_level.txt
llm_provider_factory-0.6.0.dist-info/RECORD
