Metadata-Version: 2.4
Name: llm-provider-factory
Version: 0.6.0
Summary: A unified interface for multiple LLM providers with image generation and speech-to-text support (OpenAI, Anthropic, Gemini, VertexAI, Ollama + DALL-E, Replicate, Whisper, Google Speech)
Author-email: Sadık Hanecioglu <sadik@example.com>
License-Expression: MIT
Project-URL: Homepage, https://github.com/sadikhanecioglu/llmfactory.py
Project-URL: Repository, https://github.com/sadikhanecioglu/llmfactory.py
Project-URL: Documentation, https://github.com/sadikhanecioglu/llmfactory.py#readme
Project-URL: Issues, https://github.com/sadikhanecioglu/llmfactory.py/issues
Keywords: llm,ai,openai,anthropic,gemini,ollama,local-llm,language-model,factory-pattern,image-generation,dalle,replicate,stable-diffusion
Classifier: Development Status :: 3 - Alpha
Classifier: Intended Audience :: Developers
Classifier: Programming Language :: Python :: 3
Classifier: Programming Language :: Python :: 3.8
Classifier: Programming Language :: Python :: 3.9
Classifier: Programming Language :: Python :: 3.10
Classifier: Programming Language :: Python :: 3.11
Classifier: Programming Language :: Python :: 3.12
Classifier: Topic :: Software Development :: Libraries :: Python Modules
Classifier: Topic :: Scientific/Engineering :: Artificial Intelligence
Requires-Python: >=3.8
License-File: LICENSE
Requires-Dist: openai>=1.0.0
Requires-Dist: anthropic>=0.39.0
Requires-Dist: httpx>=0.24.0
Requires-Dist: pydantic>=2.0.0
Requires-Dist: typing-extensions>=4.0.0
Provides-Extra: vertexai
Requires-Dist: google-generativeai>=0.3.0; extra == "vertexai"
Requires-Dist: google-cloud-aiplatform>=1.0.0; extra == "vertexai"
Requires-Dist: google-genai>=1.0.0; extra == "vertexai"
Provides-Extra: ollama
Provides-Extra: image
Requires-Dist: replicate>=0.22.0; extra == "image"
Provides-Extra: speech
Requires-Dist: google-cloud-speech>=2.18.0; extra == "speech"
Provides-Extra: dev
Requires-Dist: pytest>=7.0.0; extra == "dev"
Requires-Dist: pytest-cov>=4.0.0; extra == "dev"
Requires-Dist: pytest-asyncio>=0.21.0; extra == "dev"
Requires-Dist: black>=23.0.0; extra == "dev"
Requires-Dist: isort>=5.12.0; extra == "dev"
Requires-Dist: flake8>=6.0.0; extra == "dev"
Requires-Dist: mypy>=1.0.0; extra == "dev"
Provides-Extra: all
Requires-Dist: google-generativeai>=0.3.0; extra == "all"
Requires-Dist: google-cloud-aiplatform>=1.0.0; extra == "all"
Requires-Dist: google-genai>=1.0.0; extra == "all"
Requires-Dist: google-cloud-speech>=2.18.0; extra == "all"
Requires-Dist: replicate>=0.22.0; extra == "all"
Requires-Dist: pytest>=7.0.0; extra == "all"
Requires-Dist: pytest-cov>=4.0.0; extra == "all"
Requires-Dist: pytest-asyncio>=0.21.0; extra == "all"
Requires-Dist: black>=23.0.0; extra == "all"
Requires-Dist: isort>=5.12.0; extra == "all"
Requires-Dist: flake8>=6.0.0; extra == "all"
Requires-Dist: mypy>=1.0.0; extra == "all"
Dynamic: license-file
